rand_archive-0.2.3.dist-info/METADATA
rand_archive-0.2.3.dist-info/WHEEL
rand_archive/rand_archive.pyi
rand_archive/__init__.py
rand_archive/__pycache__/__init__.cpython-310.pyc
rand_archive/rand_archive.cp38-win_amd64.pyd
rand_archive-0.2.3.dist-info/RECORD
